{
    "label1": {
        "type": "label",
        "value": "BACKGROUND AND GRID COLORS:"
    },

            "backgroundColor1": {
                "text": "Background gradient color 1",
                "type": "color",
                "value": "#0C0C0C"
            },

            "backgroundColor2": {
                "text": "Background gradient color 2",
                "type": "color",
                "value": "#242424"
            },

            "hexagonsColor1": {
                "text": "Hexagons gradient color 1",
                "type": "color",
                "value": "#384048"
            },

            "hexagonsColor2": {
                "text": "Hexagons gradient Color 2",
                "type": "color",
                "value": "#54606C"
            },

            "HexagonsEdgeColor": {
                "text": "Hexagons edge color",
                "type": "color",
                "value": "#C0C0C0"
            },

    "label2": {
        "type": "label",
        "value": "HEXAGONS:"
    },

            "hexagonsSize": {
                "text": "Hexagons size",
                "type": "slider",
                "max": 250,
                "min": 10,
                "tick": 241,
                "value": 50
            },

            "hexagonsMargin": {
                "text": "Hexagons margin",
                "type": "slider",
                "max": 50,
                "min": 0,
                "tick": 51,
                "value": 5
            },

    "label3": {
        "type": "label",
        "value": "CURSOR LIGHT:"
    },

            "cursorLightColor": {
                "text": "Cursor light start color",
                "type": "color",
                "value": "#6080FF"
            },

            "cursorLightColorHueChange": {
                "text": "Cursor light color change per second in degrees",
                "type": "slider",
                "max": 360,
                "min": -360,
                "tick": 721,
                "value": 18
            },

            "cursorLightSize": {
                "text": "Cursor light size",
                "type": "slider",
                "max": 200,
                "min": 0,
                "tick": 201,
                "value": 75
            },

            "cursorLightTrailLenght": {
                "text": "Cursor light trail length",
                "type": "slider",
                "max": 100,
                "min": 0,
                "tick": 101,
                "value": 25
            },

    "label4": {
        "type": "label",
        "value": "RANDOM LIGHTS:"
    },
    
            "randomLightsCount": {
                "text": "Random lights count",
                "type": "slider",
                "max": 10,
                "min": 0,
                "tick": 11,
                "value": 2
            },

            "randomLightsColor": {
                "text": "Random lights start color",
                "type": "color",
                "value": "#FF6000"
            },

            "randomLightsColorHueRange": {
                "text": "Random lights start color max hue range in degrees",
                "type": "slider",
                "max": 360,
                "min": -360,
                "tick": 721,
                "value": -64
            },

            "randomLightsColorHueChange": {
                "text": "Random lights color change per second in degrees",
                "type": "slider",
                "max": 360,
                "min": -360,
                "tick": 721,
                "value": 0
            },

            "randomLightsSizeMin": {
                "text": "Random lights size min",
                "type": "slider",
                "max": 100,
                "min": 5,
                "tick": 96,
                "value": 20
            },

            "randomLightsSizeMax": {
                "text": "Random lights size max",
                "type": "slider",
                "max": 100,
                "min": 5,
                "tick": 96,
                "value": 40
            },

            "randomLightsSpeedMin": {
                "text": "Random lights speed min",
                "type": "slider",
                "max": 50,
                "min": 1,
                "tick": 50,
                "value": 3
            },

            "randomLightsSpeedMax": {
                "text": "Random lights speed max",
                "type": "slider",
                "max": 50,
                "min": 1,
                "tick": 50,
                "value": 5
            },

            "randomLightsTrailLenght": {
                "text": "Random lights trail lenght (large values are performance heavy!)",
                "type": "slider",
                "max": 100,
                "min": 1,
                "tick": 101,
                "value": 50
            },

    "label5": {
        "type": "label",
        "value": "CLICK LIGHTS:"
    },
    
            "clickLightsCount": {
                "text": "Click lights count",
                "type": "slider",
                "max": 20,
                "min": 0,
                "tick": 21,
                "value": 10
            },

            "clickLightsColor": {
                "text": "Click lights start color",
                "type": "color",
                "value": "#6080FF"
            },

            "clickLightsColorHueRange": {
                "text": "Click lights start color max hue range in degrees",
                "type": "slider",
                "max": 360,
                "min": -360,
                "tick": 721,
                "value": 32
            },

            "clickLightsMatchCursor": {
                "type": "checkbox",
                "value": true,
                "text": "Match start color with cursor light"
            },

            "clickLightsColorHueChange": {
                "text": "Click lights color change per second in degrees",
                "type": "slider",
                "max": 360,
                "min": -360,
                "tick": 721,
                "value": 30
            },

            "clickLightsSizeMin": {
                "text": "Click lights size min",
                "type": "slider",
                "max": 100,
                "min": 5,
                "tick": 96,
                "value": 10
            },

            "clickLightsSizeMax": {
                "text": "Click lights size max",
                "type": "slider",
                "max": 100,
                "min": 5,
                "tick": 96,
                "value": 15
            },

            "clickLightsSpeedMin": {
                "text": "Click lights speed min",
                "type": "slider",
                "max": 50,
                "min": 1,
                "tick": 50,
                "value": 25
            },

            "clickLightsSpeedMax": {
                "text": "Click lights speed max",
                "type": "slider",
                "max": 50,
                "min": 1,
                "tick": 50,
                "value": 25
            },

            "clickLightsTrailLenght": {
                "text": "Click lights lenght (large values are performance heavy!)",
                "type": "slider",
                "max": 100,
                "min": 0,
                "tick": 101,
                "value": 10
            }
}